{
  "title": "Desk hardening \u2014 chase to floor",
  "recorded_at": "2026-07-23T13:48:32.420074+00:00",
  "parent_sha": "f6a363dbcc33546e4dda11975f83d211e67b90f0",
  "unit_tests": {
    "passed": 56,
    "skipped_sha_during_prepush": 1
  },
  "invariants_landed": [
    "DataCite + HuggingFace promote: query_ready only after smoke ok (no extension-only instant)",
    "GET authorize for sensitive library paths",
    "HTTP collect uses open_pinned_public_url (DNS pin + Host/SNI)",
    "Playwright route fulfills via DNS-pinned Node HTTP (connect-time pin)",
    "Windows packaging ships network_policy.py sibling with remote_collect.py",
    "YzuOrchestrator.submit always runs enforce_execution_submit (path-independent)",
    "approve_collect explicitly approves after pending submit",
    "archive_after_job stamps _ops_internal",
    "desk auth: constant-time token compare; session bootstrap requires Origin/Referer",
    "faculty may auto-approve source_probe only",
    "fail-closed auth on all mutating /library and /yzu POSTs",
    "generic_url_scrape.mjs installNetworkGuard aborts private/metadata hosts",
    "in-process desk write rate limit (429)",
    "local_json_file empty [] returns 0 rows (no fake value wrapper)",
    "magic never auto-executes http_manifest/scraper/datacite collects",
    "prove_desk_hardening.sh end-to-end gate",
    "prove_query_smoke uses ephemeral registry stub; rejects empty arrays + error envelopes",
    "source_probe + generic_url_scrape URL public validation at orchestrator"
  ],
  "live_dns_pin_smoke": {
    "url": "https://api.github.com/zen",
    "http_status": 200,
    "pinned_address": "20.27.177.116",
    "ok": true
  },
  "still_open": [
    "multi-tenant identity / per-faculty authN (single shared desk token today)",
    "full AI pipeline compiler (product, not a security gate)",
    "public internet unattended SLOs (desk is Tailscale-internal)"
  ],
  "backend_sha": "9beac5a754d87ca3c3737c179e2d473500cce019",
  "live_hostile_after_restart": [
    {
      "name": "faculty_pipeline",
      "http": 400,
      "ok": true
    },
    {
      "name": "ops_smuggle",
      "http": 400,
      "ok": true
    },
    {
      "name": "named_vendor",
      "http": 400,
      "ok": true
    },
    {
      "name": "auto_approve_force",
      "http": 200,
      "status": "pending_approval",
      "job_id": "82dc430ec777",
      "ok": true
    }
  ],
  "services_restarted": [
    "research-drive-front-door.service",
    "yzu-cluster-worker.service"
  ]
}
